brendapyrser/__init__.py
brendapyrser/parser.py
brendapyrser-0.0.2.dist-info/LICENSE
brendapyrser-0.0.2.dist-info/METADATA
brendapyrser-0.0.2.dist-info/WHEEL
brendapyrser-0.0.2.dist-info/top_level.txt
brendapyrser-0.0.2.dist-info/RECORD
