Metadata-Version: 2.1
Name: brendapyrser
Version: 0.0.2
Summary: Tools to parse the BRENDA database
Home-page: https://github.com/robaina/BRENDA_database
Author: Semidán Robaina Estévez
Author-email: srobaina@ull.edu.es
Maintainer: Semidán Robaina Estévez
Maintainer-email: srobaina@ull.edu.es
License: Creative Commons Attribution 4.0 International
Platform: UNKNOWN
License-File: LICENSE
Requires-Dist: numpy
Requires-Dist: pandas
